Classfile /D:/MyProgram/java/SpringDmeo/target/test-classes/Base.class
  Last modified 2017-3-23; size 503 bytes
  MD5 checksum 87580fd2ce309bdef38b4eac83e7203e
  Compiled from "Base.java"
public class Base
  SourceFile: "Base.java"
  minor version: 0
  major version: 51
  flags: ACC_PUBLIC, ACC_SUPER
Constant pool:
   #1 = Methodref          #7.#20         //  java/lang/Object."<init>":()V
   #2 = Fieldref           #6.#21         //  Base.i:I
   #3 = Fieldref           #22.#23        //  java/lang/System.out:Ljava/io/PrintStream;
   #4 = Methodref          #24.#25        //  java/io/PrintStream.println:(I)V
   #5 = Methodref          #6.#26         //  Base.display:()V
   #6 = Class              #27            //  Base
   #7 = Class              #28            //  java/lang/Object
   #8 = Utf8               i
   #9 = Utf8               I
  #10 = Utf8               <init>
  #11 = Utf8               ()V
  #12 = Utf8               Code
  #13 = Utf8               LineNumberTable
  #14 = Utf8               LocalVariableTable
  #15 = Utf8               this
  #16 = Utf8               LBase;
  #17 = Utf8               display
  #18 = Utf8               SourceFile
  #19 = Utf8               Base.java
  #20 = NameAndType        #10:#11        //  "<init>":()V
  #21 = NameAndType        #8:#9          //  i:I
  #22 = Class              #29            //  java/lang/System
  #23 = NameAndType        #30:#31        //  out:Ljava/io/PrintStream;
  #24 = Class              #32            //  java/io/PrintStream
  #25 = NameAndType        #33:#34        //  println:(I)V
  #26 = NameAndType        #17:#11        //  display:()V
  #27 = Utf8               Base
  #28 = Utf8               java/lang/Object
  #29 = Utf8               java/lang/System
  #30 = Utf8               out
  #31 = Utf8               Ljava/io/PrintStream;
  #32 = Utf8               java/io/PrintStream
  #33 = Utf8               println
  #34 = Utf8               (I)V
{
  private int i;
    flags: ACC_PRIVATE


  public Base();
    flags: ACC_PUBLIC
    Code:
      stack=2, locals=1, args_size=1
         0: aload_0       
         1: invokespecial #1                  // Method java/lang/Object."<init>":()V
         4: aload_0       
         5: iconst_2      
         6: putfield      #2                  // Field i:I
         9: getstatic     #3                  // Field java/lang/System.out:Ljava/io/PrintStream;
        12: aload_0       
        13: getfield      #2                  // Field i:I
        16: invokevirtual #4                  // Method java/io/PrintStream.println:(I)V
        19: aload_0       
        20: invokevirtual #5                  // Method display:()V
        23: return        
      LineNumberTable:
        line 9: 0
        line 8: 4
        line 10: 9
        line 11: 19
        line 12: 23
      LocalVariableTable:
        Start  Length  Slot  Name   Signature
               0      24     0  this   LBase;

  public void display();
    flags: ACC_PUBLIC
    Code:
      stack=2, locals=1, args_size=1
         0: getstatic     #3                  // Field java/lang/System.out:Ljava/io/PrintStream;
         3: aload_0       
         4: getfield      #2                  // Field i:I
         7: invokevirtual #4                  // Method java/io/PrintStream.println:(I)V
        10: return        
      LineNumberTable:
        line 14: 0
        line 15: 10
      LocalVariableTable:
        Start  Length  Slot  Name   Signature
               0      11     0  this   LBase;
}
